{
  "type": "Feature",
  "properties": {
    "gn:asciiname":"Lomba",
    "gn:country_code":"CV",
    "gn:dem":703,
    "gn:feature_class":"P",
    "gn:feature_code":"PPL",
    "gn:name":"Lomba",
    "gn:population":0,
    "gn:timezone":"Atlantic/Cape_Verde",
    "iso:country":"CV",
    "name:cat_x_preferred":[
        "Lomba"
    ],
    "name:por_x_preferred":[
        "Lomba"
    ],
    "wof:name":"Lomba",
    "wof:placetype":"locality"
},
  "geometry": {"coordinates":[-24.45,14.969],"type":"Point"}
}