{
  "type": "Feature",
  "properties": {
    "gn:admin1_code":"20",
    "gn:asciiname":"Portal",
    "gn:country_code":"CV",
    "gn:dem":170,
    "gn:feature_class":"P",
    "gn:feature_code":"PPL",
    "gn:name":"Portal",
    "gn:population":0,
    "gn:timezone":"Atlantic/Cape_Verde",
    "iso:country":"CV",
    "name:aze_x_preferred":[
        "Portal"
    ],
    "name:cat_x_preferred":[
        "Portal"
    ],
    "name:ceb_x_preferred":[
        "Portal"
    ],
    "name:dan_x_preferred":[
        "Portal"
    ],
    "name:deu_x_preferred":[
        "Portal"
    ],
    "name:fas_x_preferred":[
        "\u067e\u0648\u0631\u062a\u0627\u0644"
    ],
    "name:fin_x_preferred":[
        "Portaali"
    ],
    "name:fra_x_preferred":[
        "Portal"
    ],
    "name:heb_x_preferred":[
        "\u05e4\u05d5\u05e8\u05d8\u05dc"
    ],
    "name:hin_x_preferred":[
        "\u092a\u094b\u0930\u094d\u091f\u0932"
    ],
    "name:hrv_x_preferred":[
        "Portal"
    ],
    "name:hye_x_preferred":[
        "\u054a\u0578\u0580\u057f\u0561\u056c"
    ],
    "name:ina_x_preferred":[
        "Portal"
    ],
    "name:ita_x_preferred":[
        "Portal"
    ],
    "name:jpn_x_preferred":[
        "\u30dd\u30fc\u30bf\u30eb"
    ],
    "name:kat_x_preferred":[
        "\u10de\u10dd\u10e0\u10e2\u10d0\u10da\u10d8"
    ],
    "name:kir_x_preferred":[
        "\u041f\u043e\u0440\u0442\u0430\u043b"
    ],
    "name:nld_x_preferred":[
        "Portal"
    ],
    "name:pol_x_preferred":[
        "Portal"
    ],
    "name:por_x_preferred":[
        "Portal"
    ],
    "name:rus_x_preferred":[
        "\u041f\u043e\u0440\u0442\u0430\u043b"
    ],
    "name:slk_x_preferred":[
        "Portal"
    ],
    "name:spa_x_preferred":[
        "Portal"
    ],
    "name:sqi_x_preferred":[
        "Portali"
    ],
    "name:srp_x_preferred":[
        "\u041f\u043e\u0440\u0442\u0430\u043b"
    ],
    "name:swe_x_preferred":[
        "Portal"
    ],
    "name:ukr_x_preferred":[
        "\u041f\u043e\u0440\u0442\u0430\u043b"
    ],
    "name:vol_x_preferred":[
        "Portal"
    ],
    "wof:name":"Portal",
    "wof:placetype":"locality"
},
  "geometry": {"coordinates":[-23.71667,15.25],"type":"Point"}
}