{
  "type": "Feature",
  "properties": {
    "gn:admin1_code":"04",
    "gn:asciiname":"Figueira Seca",
    "gn:country_code":"CV",
    "gn:dem":37,
    "gn:feature_class":"P",
    "gn:feature_code":"PPL",
    "gn:name":"Figueira Seca",
    "gn:population":0,
    "gn:timezone":"Atlantic/Cape_Verde",
    "iso:country":"CV",
    "wof:name":"Figueira Seca",
    "wof:placetype":"locality"
},
  "geometry": {"coordinates":[-23.1448,15.15624],"type":"Point"}
}