{
  "type": "Feature",
  "properties": {
    "gn:admin1_code":"11",
    "gn:asciiname":"Ponta da Cruz",
    "gn:country_code":"CV",
    "gn:dem":4,
    "gn:feature_class":"P",
    "gn:feature_code":"PPL",
    "gn:name":"Ponta da Cruz",
    "gn:population":0,
    "gn:timezone":"Atlantic/Cape_Verde",
    "iso:country":"CV",
    "wof:name":"Ponta da Cruz",
    "wof:placetype":"locality"
},
  "geometry": {"coordinates":[-24.74546,16.74633],"type":"Point"}
}