{
  "type": "Feature",
  "properties": {
    "gn:asciiname":"Garca de Cima",
    "gn:country_code":"CV",
    "gn:dem":491,
    "gn:feature_class":"P",
    "gn:feature_code":"PPLL",
    "gn:name":"Gar\u00e7a de Cima",
    "gn:population":0,
    "gn:timezone":"Atlantic/Cape_Verde",
    "iso:country":"CV",
    "wof:name":"Garca de Cima",
    "wof:placetype":"locality"
},
  "geometry": {"coordinates":[-25.165,17.114],"type":"Point"}
}