{
  "type": "Feature",
  "properties": {
    "gn:asciiname":"Tira Chapeu",
    "gn:country_code":"CV",
    "gn:dem":26,
    "gn:feature_class":"P",
    "gn:feature_code":"PPL",
    "gn:name":"Tira Chapeu",
    "gn:population":0,
    "gn:timezone":"Atlantic/Cape_Verde",
    "iso:country":"CV",
    "wof:name":"Tira Chapeu",
    "wof:placetype":"locality"
},
  "geometry": {"coordinates":[-23.52278,14.91389],"type":"Point"}
}