{
  "type": "Feature",
  "properties": {
    "gn:admin1_code":"19",
    "gn:asciiname":"Palha Carga",
    "gn:country_code":"CV",
    "gn:dem":321,
    "gn:feature_class":"P",
    "gn:feature_code":"PPL",
    "gn:name":"Palha Carga",
    "gn:population":0,
    "gn:timezone":"Atlantic/Cape_Verde",
    "iso:country":"CV",
    "name:cat_x_preferred":[
        "Palha Carga"
    ],
    "wof:name":"Palha Carga",
    "wof:placetype":"locality"
},
  "geometry": {"coordinates":[-23.66667,15.21667],"type":"Point"}
}