{
  "type": "Feature",
  "properties": {
    "gn:admin1_code":"18",
    "gn:asciiname":"Inhuco",
    "gn:country_code":"CV",
    "gn:dem":721,
    "gn:feature_class":"P",
    "gn:feature_code":"PPL",
    "gn:name":"Inhuco",
    "gn:population":0,
    "gn:timezone":"Atlantic/Cape_Verde",
    "iso:country":"CV",
    "name:und_x_variant":[
        "Nhuco",
        "Inhuco"
    ],
    "wof:name":"Inhuco",
    "wof:placetype":"locality"
},
  "geometry": {"coordinates":[-24.45,14.93333],"type":"Point"}
}