{
  "type": "Feature",
  "properties": {
    "gn:admin1_code":"27",
    "gn:asciiname":"Tarrafal de Sao Nicolau",
    "gn:country_code":"CV",
    "gn:dem":4,
    "gn:feature_class":"P",
    "gn:feature_code":"PPLA",
    "gn:name":"Tarrafal de S\u00e3o Nicolau",
    "gn:population":5039,
    "gn:timezone":"Atlantic/Cape_Verde",
    "iso:country":"CV",
    "name:und_x_variant":[
        "Tarrafal"
    ],
    "wof:name":"Tarrafal de Sao Nicolau",
    "wof:placetype":"locality",
    "wof:population":5039
},
  "geometry": {"coordinates":[-24.35793,16.56622],"type":"Point"}
}