{
  "type": "Feature",
  "properties": {
    "gn:admin1_code":"11",
    "gn:asciiname":"Mateuzinho",
    "gn:country_code":"CV",
    "gn:dem":342,
    "gn:feature_class":"P",
    "gn:feature_code":"PPL",
    "gn:name":"Mateuzinho",
    "gn:population":0,
    "gn:timezone":"Atlantic/Cape_Verde",
    "iso:country":"CV",
    "name:und_x_variant":[
        "Mateusinho",
        "Mateuzinho"
    ],
    "wof:name":"Mateuzinho",
    "wof:placetype":"locality"
},
  "geometry": {"coordinates":[-24.93559,16.85988],"type":"Point"}
}