{
  "type": "Feature",
  "properties": {
    "gn:admin1_code":"21",
    "gn:asciiname":"Queimado",
    "gn:country_code":"CV",
    "gn:dem":1352,
    "gn:feature_class":"P",
    "gn:feature_code":"PPL",
    "gn:name":"Queimado",
    "gn:population":0,
    "gn:timezone":"Atlantic/Cape_Verde",
    "iso:country":"CV",
    "wof:name":"Queimado",
    "wof:placetype":"locality"
},
  "geometry": {"coordinates":[-25.23333,16.98333],"type":"Point"}
}