{
  "type": "Feature",
  "properties": {
    "gn:admin1_code":"13",
    "gn:asciiname":"Fajazinha",
    "gn:country_code":"CV",
    "gn:dem":-9999,
    "gn:feature_class":"P",
    "gn:feature_code":"PPL",
    "gn:name":"Faj\u00e3zinha",
    "gn:population":0,
    "gn:timezone":"Atlantic/Cape_Verde",
    "iso:country":"CV",
    "name:cat_x_preferred":[
        "Faj\u00e3zinha"
    ],
    "name:por_x_preferred":[
        "Faj\u00e3zinha"
    ],
    "name:und_x_variant":[
        "Fajasinhas",
        "Faj\u00e3sinha",
        "Faj\u00e3zinha"
    ],
    "wof:name":"Fajazinha",
    "wof:placetype":"locality"
},
  "geometry": {"coordinates":[-24.35,15.05],"type":"Point"}
}