{
  "type": "Feature",
  "properties": {
    "gn:admin1_code":"24",
    "gn:asciiname":"Fonte Aleixo",
    "gn:country_code":"CV",
    "gn:dem":298,
    "gn:feature_class":"P",
    "gn:feature_code":"PPL",
    "gn:name":"Fonte Aleixo",
    "gn:population":0,
    "gn:timezone":"Atlantic/Cape_Verde",
    "iso:country":"CV",
    "wof:name":"Fonte Aleixo",
    "wof:placetype":"locality"
},
  "geometry": {"coordinates":[-24.36667000000001,14.83333],"type":"Point"}
}