{
  "type": "Feature",
  "properties": {
    "gn:admin1_code":"27",
    "gn:asciiname":"Palhal",
    "gn:country_code":"CV",
    "gn:dem":948,
    "gn:feature_class":"P",
    "gn:feature_code":"PPL",
    "gn:name":"Palhal",
    "gn:population":0,
    "gn:timezone":"Atlantic/Cape_Verde",
    "iso:country":"CV",
    "wof:name":"Palhal",
    "wof:placetype":"locality"
},
  "geometry": {"coordinates":[-24.35,16.61667000000001],"type":"Point"}
}