{
  "type": "Feature",
  "properties": {
    "gn:admin1_code":"13",
    "gn:asciiname":"Ribeira Ilheu",
    "gn:country_code":"CV",
    "gn:dem":442,
    "gn:feature_class":"P",
    "gn:feature_code":"PPL",
    "gn:name":"Ribeira Ilh\u00e9u",
    "gn:population":0,
    "gn:timezone":"Atlantic/Cape_Verde",
    "iso:country":"CV",
    "name:und_x_variant":[
        "Ribeira Ilh\u00e9u"
    ],
    "wof:name":"Ribeira Ilheu",
    "wof:placetype":"locality"
},
  "geometry": {"coordinates":[-24.38333,15.03333],"type":"Point"}
}