{
  "type": "Feature",
  "properties": {
    "gn:admin1_code":"27",
    "gn:asciiname":"Telha",
    "gn:country_code":"CV",
    "gn:dem":14,
    "gn:feature_class":"P",
    "gn:feature_code":"PPL",
    "gn:name":"Telha",
    "gn:population":0,
    "gn:timezone":"Atlantic/Cape_Verde",
    "iso:country":"CV",
    "wof:name":"Telha",
    "wof:placetype":"locality"
},
  "geometry": {"coordinates":[-24.35592,16.56201],"type":"Point"}
}