{
  "type": "Feature",
  "properties": {
    "gn:admin1_code":"27",
    "gn:asciiname":"Telha",
    "gn:country_code":"CV",
    "gn:dem":14,
    "gn:feature_class":"P",
    "gn:feature_code":"PPL",
    "gn:name":"Telha",
    "gn:population":0,
    "gn:timezone":"Atlantic/Cape_Verde",
    "iso:country":"CV",
    "name:bpy_x_preferred":[
        "\u099f\u09af\u09bc\u09c7\u09b2\u09b9\u09be"
    ],
    "name:ceb_x_preferred":[
        "Telha"
    ],
    "name:epo_x_preferred":[
        "Telha"
    ],
    "name:eus_x_preferred":[
        "Telha"
    ],
    "name:fra_x_preferred":[
        "Telha"
    ],
    "name:ita_x_preferred":[
        "Telha"
    ],
    "name:nld_x_preferred":[
        "Telha"
    ],
    "name:nor_x_preferred":[
        "Telha"
    ],
    "name:por_x_preferred":[
        "Telha"
    ],
    "name:ron_x_preferred":[
        "Telha"
    ],
    "name:rus_x_preferred":[
        "\u0422\u0435\u043b\u044c\u044f"
    ],
    "name:spa_x_preferred":[
        "Telha"
    ],
    "name:vie_x_preferred":[
        "Telha"
    ],
    "name:vol_x_preferred":[
        "Telha"
    ],
    "name:war_x_preferred":[
        "Telha"
    ],
    "name:zho_x_preferred":[
        "\u7279\u5229\u4e9e"
    ],
    "wof:name":"Telha",
    "wof:placetype":"locality"
},
  "geometry": {"coordinates":[-24.35592,16.56201],"type":"Point"}
}