{
  "type": "Feature",
  "properties": {
    "gn:admin1_code":"20",
    "gn:asciiname":"Ribeirao Sal",
    "gn:country_code":"CV",
    "gn:dem":395,
    "gn:feature_class":"P",
    "gn:feature_code":"PPL",
    "gn:name":"Ribeir\u00e3o Sal",
    "gn:population":0,
    "gn:timezone":"Atlantic/Cape_Verde",
    "iso:country":"CV",
    "wof:name":"Ribeirao Sal",
    "wof:placetype":"locality"
},
  "geometry": {"coordinates":[-23.68333,15.23333],"type":"Point"}
}