{
  "type": "Feature",
  "properties": {
    "gn:admin1_code":"07",
    "gn:asciiname":"Cruzinha",
    "gn:country_code":"CV",
    "gn:dem":99,
    "gn:feature_class":"P",
    "gn:feature_code":"PPL",
    "gn:name":"Cruzinha",
    "gn:population":0,
    "gn:timezone":"Atlantic/Cape_Verde",
    "iso:country":"CV",
    "name:cat_x_preferred":[
        "Cruzinha"
    ],
    "name:por_x_preferred":[
        "Cruzinha"
    ],
    "wof:name":"Cruzinha",
    "wof:placetype":"locality"
},
  "geometry": {"coordinates":[-25.16667,17.16667],"type":"Point"}
}