{
  "type": "Feature",
  "properties": {
    "gn:admin1_code":"22",
    "gn:asciiname":"Morre Braz",
    "gn:country_code":"CV",
    "gn:dem":52,
    "gn:feature_class":"P",
    "gn:feature_code":"PPL",
    "gn:name":"Morre Braz",
    "gn:population":0,
    "gn:timezone":"Atlantic/Cape_Verde",
    "iso:country":"CV",
    "wof:name":"Morre Braz",
    "wof:placetype":"locality"
},
  "geometry": {"coordinates":[-24.19412,16.63341],"type":"Point"}
}