{
  "type": "Feature",
  "properties": {
    "gn:asciiname":"Mato Ingles",
    "gn:country_code":"CV",
    "gn:dem":164,
    "gn:feature_class":"P",
    "gn:feature_code":"PPL",
    "gn:name":"Mato Ingles",
    "gn:population":0,
    "gn:timezone":"Atlantic/Cape_Verde",
    "iso:country":"CV",
    "wof:name":"Mato Ingles",
    "wof:placetype":"locality"
},
  "geometry": {"coordinates":[-24.94833,16.86083],"type":"Point"}
}