{
  "type": "Feature",
  "properties": {
    "gn:asciiname":"Alto Sao Nicolau",
    "gn:country_code":"CV",
    "gn:dem":16,
    "gn:feature_class":"P",
    "gn:feature_code":"PPL",
    "gn:name":"Alto Sao Nicolau",
    "gn:population":0,
    "gn:timezone":"Atlantic/Cape_Verde",
    "iso:country":"CV",
    "wof:name":"Alto Sao Nicolau",
    "wof:placetype":"locality"
},
  "geometry": {"coordinates":[-24.99098,16.88944],"type":"Point"}
}