{
  "type": "Feature",
  "properties": {
    "iso:country":"CV",
    "name:cat_x_preferred":[
        "Palmeira"
    ],
    "name:deu_x_preferred":[
        "Palmeira"
    ],
    "name:dut_x_preferred":[
        "Palmeira"
    ],
    "name:eng_x_preferred":[
        "Palmeira"
    ],
    "name:ger_x_preferred":[
        "Palmeira"
    ],
    "name:nds_x_preferred":[
        "Palmeira"
    ],
    "name:por_x_preferred":[
        "Palmeira"
    ],
    "qs:gn_country":"CV",
    "qs:gn_fcode":"PPL",
    "qs:gn_pop":0,
    "qs:name":"Palmeira",
    "qs:name_adm0":"Cabo Verde",
    "qs:name_adm1":"Sal",
    "qs:photos":228,
    "qs:photos_1k":46,
    "qs:photos_9k":1,
    "qs:photos_9r":4,
    "qs:photos_all":228,
    "qs:photos_sr":4,
    "qs:placetype":"Town",
    "qs:pop_sr":"0",
    "qs:woe_adm0":23424794,
    "wd:wordcount":64,
    "wof:name":"Palmeira",
    "wof:placetype":"locality"
},
  "geometry": {"coordinates":[-22.98333,16.76667],"type":"Point"}
}