{
  "type": "Feature",
  "properties": {
    "gn:admin1_code":"08",
    "gn:asciiname":"Beirona",
    "gn:country_code":"CV",
    "gn:dem":4,
    "gn:feature_class":"P",
    "gn:feature_code":"PPL",
    "gn:name":"Beirona",
    "gn:population":0,
    "gn:timezone":"Atlantic/Cape_Verde",
    "iso:country":"CV",
    "wof:name":"Beirona",
    "wof:placetype":"locality"
},
  "geometry": {"coordinates":[-22.93333,16.68333],"type":"Point"}
}